wavedenoiser/__init__.py
wavedenoiser/wavedenoiser.py
wavedenoiser/model/__init__.py
wavedenoiser/model/large.ckpt
wavedenoiser-0.2.0.dist-info/licenses/LICENSE
wavedenoiser-0.2.0.dist-info/METADATA
wavedenoiser-0.2.0.dist-info/WHEEL
wavedenoiser-0.2.0.dist-info/top_level.txt
wavedenoiser-0.2.0.dist-info/RECORD
